[
  {
    "content": "Fix bracket padding inconsistency on /welcome (frame-component23 + reviews-area1)",
    "status": "completed"
  },
  {
    "content": "Run comprehensive backend testing (all critical APIs: auth, google reviews, google client-id, customer-auth)",
    "status": "in_progress"
  },
  {
    "content": "Run comprehensive frontend testing (4 cabinets + public pages + post-merge regression)",
    "status": "pending"
  },
  {
    "content": "Address any high/medium priority bugs from testing reports",
    "status": "pending"
  },
  {
    "content": "Final pre-deploy verification + summary",
    "status": "pending"
  }
]